mongo_jsonschema/__init__.py
mongo_jsonschema/__main__.py
mongo_jsonschema/mongo_jsonschema.py
mongo_jsonschema-0.1.4.dist-info/LICENSE
mongo_jsonschema-0.1.4.dist-info/METADATA
mongo_jsonschema-0.1.4.dist-info/WHEEL
mongo_jsonschema-0.1.4.dist-info/RECORD
