Metadata-Version: 2.1
Name: mongo-jsonschema
Version: 0.1.4
Summary: A CLI tool and library for reverse engineering a JSONSchema from a MongoDB database.
Home-page: https://github.com/moseswynn/mongo-jsonschema
License: MIT
Author: Moses Wynn
Author-email: mail@moseswynn.com
Requires-Python: >=3.8,<4.0
Classifier: License :: OSI Approved :: MIT License
Classifier: Programming Language :: Python :: 3
Classifier: Programming Language :: Python :: 3.8
Classifier: Programming Language :: Python :: 3.9
Classifier: Programming Language :: Python :: 3.10
Classifier: Programming Language :: Python :: 3.11
Classifier: Programming Language :: Python :: 3.12
Requires-Dist: genson (>=1.2.2,<2.0.0)
Requires-Dist: pymongo (>=4.6.2,<5.0.0)
